ipapp/__init__.py
ipapp/__main__.py
ipapp/client.py
ipapp-4.0.4.dist-info/licenses/LICENSE
ipapp-4.0.4.dist-info/METADATA
ipapp-4.0.4.dist-info/WHEEL
ipapp-4.0.4.dist-info/entry_points.txt
ipapp-4.0.4.dist-info/top_level.txt
ipapp-4.0.4.dist-info/RECORD
