Metadata-Version: 2.4
Name: ipapp
Version: 4.0.4
Summary: A tiny ip.app client to query your IP, ASN, location & timezone using the 100% free IP.app API. Fast & reliable IP lookup.
Author-email: Fili <dev@fili.com>
License: MIT
Project-URL: Homepage, https://github.com/fili/ip.app
Project-URL: Repository, https://github.com/fili/ipapp-client
Project-URL: Issues, https://github.com/fili/ipapp-client/issues
Classifier: Programming Language :: Python :: 3
Classifier: License :: OSI Approved :: MIT License
Classifier: Operating System :: OS Independent
Requires-Python: >=3.8
License-File: LICENSE
Provides-Extra: dev
Requires-Dist: pytest; extra == "dev"
Dynamic: license-file
